{
	"format_version": "1.18.0",
	"minecraft:item": {
		"description": {
			"identifier": "teufel:brute_boots"
		},
		"components": {
			"minecraft:creative_category": {
				"category": "equipment",
				"parent": "itemGroup.name.boots"
			},
			"minecraft:icon": {
				"texture": "brute_boots"
			},
			"minecraft:display_name": {
				"value": "Brute Boots"
			},
			"minecraft:max_stack_size": 1,
			"minecraft:enchantable": {
				"value": 25,
				"slot": "armor_feet"
			},
			"minecraft:armor": {
				"protection": 7
			},
			"minecraft:wearable": {
				"dispensable": true,
				"slot": "slot.armor.feet"
			},
			"minecraft:durability": {
				"max_durability": 835
			}
		}
	}
}